video_fft/__init__.py
video_fft/__main__.py
video_fft/py.typed
video_fft/video_fft_calculator.py
video_fft-0.4.0.dist-info/WHEEL
video_fft-0.4.0.dist-info/entry_points.txt
video_fft-0.4.0.dist-info/METADATA
video_fft-0.4.0.dist-info/RECORD
