Metadata-Version: 2.4
Name: video-fft
Version: 0.4.0
Summary: Calculate the magnitude spectrum of a video sequence, via Fast Fourier Transform
Keywords: ffmpeg,video
Author: Werner Robitza
Author-email: Werner Robitza <werner.robitza@gmail.com>
License-Expression: MIT
Classifier: Development Status :: 4 - Beta
Classifier: Intended Audience :: Developers
Classifier: Topic :: Multimedia :: Video
Classifier: Natural Language :: English
Classifier: Programming Language :: Python :: 3
Classifier: Programming Language :: Python :: 3.9
Classifier: Programming Language :: Python :: 3.10
Classifier: Programming Language :: Python :: 3.11
Classifier: Programming Language :: Python :: 3.12
Classifier: Programming Language :: Python :: 3.13
Classifier: Programming Language :: Python :: 3.14
Requires-Dist: av
Requires-Dist: tqdm
Requires-Dist: numpy
Requires-Dist: matplotlib
Requires-Python: >=3.9
Project-URL: Homepage, https://github.com/slhck/video-fft
Project-URL: Repository, https://github.com/slhck/video-fft
